{"STN" : [{"id": "76561198383794129", "name": "Killstreakifier", "category": "killstreaks"},
            {"id": "76561199582352552", "name": "Headgear Galore", "category": "killstreaks"},
            {"id": "76561198310024994", "name": "Hat Rotator", "category": "hats"},
            {"id": "76561198309998421", "name": "Craft Hats", "category": "hats"},
            {"id": "76561198310454087", "name": "Hat Crafter", "category": "hats"},
            {"id": "76561198309976634", "name": "Pile of Hats", "category": "hats"},
            {"id": "76561198310524424", "name": "I Love Hats", "category": "hats"},
            {"id": "76561199582907694", "name": "Headwear Emporium", "category": "hats"},
            {"id": "76561198309190452", "name": "Scrap Hats", "category": "hats"},
            {"id": "76561198309291300", "name": "Hat Provider", "category": "hats"},
            {"id": "76561198309405764", "name": "Out of Hats", "category": "hats"},
            {"id": "76561198923568511", "name": "Hutständer", "category": "hats"},
            {"id": "76561198310691078", "name": "Strangifier", "category": "stranges"},
            {"id": "76561198309750232", "name": "Strange Headshots", "category": "stranges"},
            {"id": "76561198310188284", "name": "Vintage Collector", "category": "vintages"},
            {"id": "76561198311319887", "name": "Weapon Crusher", "category": "weapons"},
            {"id": "76561198311521627", "name": "Skin Painter", "category": "skins"},
            {"id": "76561199026476781", "name": "Skins for Skill", "category": "skins"},
            {"id": "76561198309246958", "name": "76561198309246958", "category": "genuines"},
            {"id": "76561198309246958", "name": "76561198309246958", "category": "genuines"}]}

